{"key": "DPLAT-DEF-12", "issuetype": "Bug", "project_key": "DPLAT", "epic_link": null, "summary": "SAP \u2014 delta sync skips records updated within 1s of last cursor", "description_md": "**Observed**:\n\nDuring delta synchronization from SAP, records that are updated within 1 second of the last cursor timestamp are being skipped. The cursor-based change detection uses `>=` comparison, but when multiple updates occur in rapid succession (sub-second), the timestamp precision causes some changes to be missed. This results in incomplete data synchronization.\n\n**Expected**:\n\nAll records modified after the last cursor position should be captured, regardless of sub-second timing. The delta sync should either:\n- Use `>` comparison with proper cursor advancement\n- Include a secondary sort key (e.g., record ID) to ensure deterministic ordering\n- Add a small time buffer (e.g., 100ms) to the cursor comparison\n\n**Repro steps**:\n\n1. Configure SAP connector with delta sync enabled\n2. Set cursor to capture changes from timestamp T\n3. At exactly T+500ms, update Record A in SAP\n4. At exactly T+800ms, update Record B in SAP\n5. At exactly T+1500ms, trigger delta sync\n6. Observe that Record A is synced but Record B is skipped\n7. Check logs for cursor advancement timing\n\n**Workaround**:\n\nManually trigger sync more frequently (every 30 seconds) to reduce the window of potential missed updates. Alternatively, run a full sync periodically to reconcile any skipped records.", "priority": "High", "status": "In Progress", "labels": ["module:connector-framework", "feature:F-A2", "behavior:defect", "severity:high", "sap", "delta-sync"], "components": ["Connector Framework"], "fix_versions": [], "affects_versions": ["v2.3"], "reporter": "qa1@amisol-demo.example", "assignee": "dev2@amisol-demo.example", "created": "2026-04-01T08:00:00Z", "updated": "2026-04-22T12:00:00Z", "resolved": null, "linked_issues": [], "linked_confluence": [], "comments": [{"author": "qa1@amisol-demo.example", "created": "2026-04-01T09:30:00Z", "body_md": "This is causing data inconsistency in production. Customer reported missing price updates for ~0.3% of products during peak trading hours. Need to prioritize fix before v2.4 release. Can we add a regression test for sub-second updates?"}]}